MANIFEST.in
VERSION
pyproject.toml
requirements.txt
setup.py
docs/source/conf.py
unimatrix/__init__.py
unimatrix.ext.cache.egg-info/PKG-INFO
unimatrix.ext.cache.egg-info/SOURCES.txt
unimatrix.ext.cache.egg-info/dependency_links.txt
unimatrix.ext.cache.egg-info/requires.txt
unimatrix.ext.cache.egg-info/top_level.txt
unimatrix/ext/__init__.py
unimatrix/ext/cache/__init__.py
unimatrix/ext/cache/base.py
unimatrix/ext/cache/exceptions.py
unimatrix/ext/cache/lock.py
unimatrix/ext/cache/manager.py
unimatrix/ext/cache/memory.py
unimatrix/ext/cache/package.json
unimatrix/ext/cache/redis.py
unimatrix/ext/cache/tests/__init__.py
unimatrix/ext/cache/tests/test_integration_noop.py
unimatrix/ext/cache/tests/test_system_noop.py
unimatrix/ext/cache/tests/test_system_redis.py
unimatrix/ext/cache/tests/test_unit_backoff.py
unimatrix/ext/cache/tests/test_unit_noop.py